<?xml version="1.0" encoding="ISO-8859-1"?>
<SCHRIFTSTUECKE xmlns="urn:in-software-com:IN-SCHRIFTSTUECKE">
	<SCHRIFTSTUECK>
		<KOPF/>
		<POSITIONEN>
			<MATERIALPOSITION>
				<AUFMASS>
					<IN_MENGE_UEBERNEHMEN>1</IN_MENGE_UEBERNEHMEN>
					<AUFMASSZEILE>
						<STICHWORT>Ergeschoss, Großraumbüro, Tür</STICHWORT>
						<TEXT>Oberfläche, Großraumbüro, Tür</TEXT>
						<ANZAHL> </ANZAHL>
						<LAENGE>0.80*2.04</LAENGE>
					</AUFMASSZEILE>
					<AUFMASSZEILE>
						<STICHWORT>Ergeschoss, Großraumbüro, Fenster</STICHWORT>
						<TEXT>Oberfläche, Großraumbüro, Fenster</TEXT>
						<ANZAHL> </ANZAHL>
						<LAENGE>0.80*1.20</LAENGE>
					</AUFMASSZEILE>
				</AUFMASS>
				<MENGE>1</MENGE>
			</MATERIALPOSITION>
			<MATERIALPOSITION>
				<AUFMASS>
					<IN_MENGE_UEBERNEHMEN>1</IN_MENGE_UEBERNEHMEN>
					<AUFMASSZEILE>
						<STICHWORT>Ergeschoss, Großraumbüro</STICHWORT>
						<TEXT>Bodenfläche, Großraumbüro</TEXT>
						<ANZAHL> </ANZAHL>
						<LAENGE>12.1</LAENGE>
					</AUFMASSZEILE>
				</AUFMASS>
				<MENGE>12.1</MENGE>
			</MATERIALPOSITION>
		</POSITIONEN>
	</SCHRIFTSTUECK>
</SCHRIFTSTUECKE>
